djdeploy/__init__.py
djdeploy/index.py
djdeploy-0.0.4.dist-info/LICENSE.txt
djdeploy-0.0.4.dist-info/METADATA
djdeploy-0.0.4.dist-info/WHEEL
djdeploy-0.0.4.dist-info/entry_points.txt
djdeploy-0.0.4.dist-info/top_level.txt
djdeploy-0.0.4.dist-info/RECORD
